{
  "_slug": "delete-problem-cross-seeds",
  "name": "Delete: problem cross-seeds",
  "trackerPattern": "*",
  "trackerDomains": [
    "*"
  ],
  "conditions": {
    "schemaVersion": "1",
    "delete": {
      "enabled": true,
      "mode": "deleteWithFilesPreserveCrossSeeds",
      "condition": {
        "operator": "AND",
        "conditions": [
          {
            "field": "CATEGORY",
            "operator": "EQUAL",
            "value": "cross-seed"
          },
          {
            "field": "STATE",
            "operator": "NOT_EQUAL",
            "value": "tracker_down"
          },
          {
            "field": "ADDED_ON",
            "operator": "GREATER_THAN_OR_EQUAL",
            "value": "3600"
          },
          {
            "operator": "OR",
            "conditions": [
              {
                "field": "STATE",
                "operator": "EQUAL",
                "value": "missingFiles"
              },
              {
                "field": "STATE",
                "operator": "EQUAL",
                "value": "stalled_downloading"
              }
            ]
          }
        ]
      }
    }
  },
  "intervalSeconds": 3600,
  "sortOrder": 13
}